minimalgpt/__init__.py
minimalgpt/modules.py
minimalgpt-0.0.9.dist-info/METADATA
minimalgpt-0.0.9.dist-info/WHEEL
minimalgpt-0.0.9.dist-info/top_level.txt
minimalgpt-0.0.9.dist-info/RECORD
